visier/__init__.py
visier/sdk/__init__.py
visier/sdk/api/__init__.py
visier/sdk/api/tenant_management/__init__.py
visier/sdk/api/tenant_management/api_client.py
visier/sdk/api/tenant_management/api_response.py
visier/sdk/api/tenant_management/configuration.py
visier/sdk/api/tenant_management/exceptions.py
visier/sdk/api/tenant_management/py.typed
visier/sdk/api/tenant_management/rest.py
visier/sdk/api/tenant_management/api/__init__.py
visier/sdk/api/tenant_management/api/tenant_management_api.py
visier/sdk/api/tenant_management/api/tenant_management_v1_api.py
visier/sdk/api/tenant_management/models/__init__.py
visier/sdk/api/tenant_management/models/all_tenants_status_apidto.py
visier/sdk/api/tenant_management/models/business_location_dto.py
visier/sdk/api/tenant_management/models/custom_property_dto.py
visier/sdk/api/tenant_management/models/custom_tenant_property_dto.py
visier/sdk/api/tenant_management/models/google_protobuf_any.py
visier/sdk/api/tenant_management/models/home_analysis_by_user_group_dto.py
visier/sdk/api/tenant_management/models/mask_message.py
visier/sdk/api/tenant_management/models/metric_validation_summary_dto.py
visier/sdk/api/tenant_management/models/module_settings_dto.py
visier/sdk/api/tenant_management/models/status.py
visier/sdk/api/tenant_management/models/tenant_detail_apidto.py
visier/sdk/api/tenant_management/models/tenant_management_api_get_response_dto.py
visier/sdk/api/tenant_management/models/tenant_management_api_list_response_dto.py
visier/sdk/api/tenant_management/models/tenant_management_api_update_request_dto.py
visier/sdk/api/tenant_management/models/tenant_management_api_update_response_dto.py
visier/sdk/api/tenant_management/models/tenant_module_dto.py
visier/sdk/api/tenant_management/models/tenant_preview_entries_summary_dto.py
visier/sdk/api/tenant_management/models/tenant_preview_entries_summary_list_dto.py
visier/sdk/api/tenant_management/models/tenant_provision_apidto.py
visier.sdk.api.tenant_management-0.0.6.dist-info/METADATA
visier.sdk.api.tenant_management-0.0.6.dist-info/WHEEL
visier.sdk.api.tenant_management-0.0.6.dist-info/top_level.txt
visier.sdk.api.tenant_management-0.0.6.dist-info/RECORD
